sshcon/__init__.py
sshcon/exceptions.py
sshcon/main.py
sshcon-0.3.3.dist-info/LICENSE
sshcon-0.3.3.dist-info/METADATA
sshcon-0.3.3.dist-info/WHEEL
sshcon-0.3.3.dist-info/top_level.txt
sshcon-0.3.3.dist-info/RECORD
