Metadata-Version: 2.1
Name: sshcon
Version: 0.3.3
Summary: SSH connector for Linux systems
Home-page: https://github.com/racoonx2p/sshcon
Author: racoonx2p
Author-email: racoonx2p@gmail.com
License: MIT
Project-URL: Bug Tracker, https://github.com/racoonx2p/sshcon/issues
Project-URL: Changelog, https://github.com/racoonx2p/sshcon/blob/master/CHANGELOG.md
Keywords: ssh
Platform: linux
Classifier: Development Status :: 3 - Alpha
Classifier: Intended Audience :: Developers
Classifier: License :: OSI Approved :: MIT License
Classifier: Operating System :: POSIX :: Linux
Classifier: Programming Language :: Python
Classifier: Programming Language :: Python :: 3.4
Classifier: Programming Language :: Python :: 3.5
Classifier: Programming Language :: Python :: 3.6
Classifier: Programming Language :: Python :: 3.7
Classifier: Programming Language :: Python :: 3.8
Classifier: Topic :: Software Development :: Libraries :: Python Modules
Requires-Python: >=3.6
Requires-Dist: ssh2-python (==0.22.0)
